mehta/__init__.py
mehta/__main__.py
mehta/client.py
mehta/helpers.py
mehta/plugins.py
mehta-1.1.6.dist-info/licenses/LICENSE
mehta-1.1.6.dist-info/METADATA
mehta-1.1.6.dist-info/WHEEL
mehta-1.1.6.dist-info/entry_points.txt
mehta-1.1.6.dist-info/top_level.txt
mehta-1.1.6.dist-info/RECORD
